llama_cloud/__init__.py
llama_cloud/_base_client.py
llama_cloud/_client.py
llama_cloud/_compat.py
llama_cloud/_constants.py
llama_cloud/_exceptions.py
llama_cloud/_files.py
llama_cloud/_models.py
llama_cloud/_polling.py
llama_cloud/_qs.py
llama_cloud/_resource.py
llama_cloud/_response.py
llama_cloud/_streaming.py
llama_cloud/_types.py
llama_cloud/_version.py
llama_cloud/pagination.py
llama_cloud/py.typed
llama_cloud/_utils/__init__.py
llama_cloud/_utils/_compat.py
llama_cloud/_utils/_datetime_parse.py
llama_cloud/_utils/_json.py
llama_cloud/_utils/_logs.py
llama_cloud/_utils/_proxy.py
llama_cloud/_utils/_reflection.py
llama_cloud/_utils/_resources_proxy.py
llama_cloud/_utils/_streams.py
llama_cloud/_utils/_sync.py
llama_cloud/_utils/_transform.py
llama_cloud/_utils/_typing.py
llama_cloud/_utils/_utils.py
llama_cloud/lib/__init__.py
llama_cloud/lib/index/__init__.py
llama_cloud/lib/index/api_utils.py
llama_cloud/lib/index/base.py
llama_cloud/lib/index/composite_retriever.py
llama_cloud/lib/index/retriever.py
llama_cloud/resources/__init__.py
llama_cloud/resources/data_sinks.py
llama_cloud/resources/data_sources.py
llama_cloud/resources/files.py
llama_cloud/resources/parsing.py
llama_cloud/resources/projects.py
llama_cloud/resources/beta/__init__.py
llama_cloud/resources/beta/agent_data.py
llama_cloud/resources/beta/beta.py
llama_cloud/resources/beta/parse_configurations.py
llama_cloud/resources/beta/sheets.py
llama_cloud/resources/beta/split.py
llama_cloud/resources/beta/batch/__init__.py
llama_cloud/resources/beta/batch/batch.py
llama_cloud/resources/beta/batch/job_items.py
llama_cloud/resources/beta/directories/__init__.py
llama_cloud/resources/beta/directories/directories.py
llama_cloud/resources/beta/directories/files.py
llama_cloud/resources/classifier/__init__.py
llama_cloud/resources/classifier/classifier.py
llama_cloud/resources/classifier/jobs.py
llama_cloud/resources/extraction/__init__.py
llama_cloud/resources/extraction/extraction.py
llama_cloud-1.2.0.dist-info/METADATA
llama_cloud-1.2.0.dist-info/WHEEL
llama_cloud-1.2.0.dist-info/licenses/LICENSE
llama_cloud-1.2.0.dist-info/RECORD
